{
  "schema_version": "1.0.0",
  "updated_at": "2026-07-23T05:44:50.872Z",
  "description": "Players excluded from match collection pipeline.",
  "players": [
    {
      "name": "옥수수",
      "wr_id": 1022,
      "reason": "user_excluded"
    },
    {
      "name": "김수환",
      "wr_id": 118,
      "reason": "user_excluded_pending_tier"
    },
    {
      "name": "김민교",
      "wr_id": 162,
      "reason": "user_excluded"
    },
    {
      "name": "박한별",
      "wr_id": 185,
      "reason": "user_excluded_pending_tier"
    },
    {
      "name": "이상호",
      "wr_id": 402,
      "reason": "user_excluded"
    },
    {
      "name": "농떼르만",
      "wr_id": 646,
      "entity_id": "eloboard:male:646",
      "reason": "user_excluded"
    },
    {
      "name": "엘사",
      "wr_id": 777,
      "entity_id": "eloboard:male:777",
      "reason": "user_excluded_pending_tier"
    },
    {
      "name": "초롱빡",
      "wr_id": 41,
      "entity_id": "eloboard:female:41",
      "reason": "user_excluded_inactive_until_affiliated"
    },
    {
      "entity_id": "eloboard:female:939",
      "wr_id": 939,
      "name": "행복짱",
      "reason": "user_excluded",
      "updated_at": "2026-03-26T08:57:45.416Z"
    },
    {
      "entity_id": "eloboard:female:951",
      "wr_id": 951,
      "name": "단이",
      "reason": "user_excluded_unneeded_for_homepage",
      "updated_at": "2026-05-15T15:03:41.507Z"
    },
    {
      "entity_id": "eloboard:female:998",
      "wr_id": 998,
      "name": "박쭈이",
      "reason": "user_excluded_unneeded_for_homepage",
      "updated_at": "2026-05-15T15:03:41.507Z"
    },
    {
      "entity_id": "eloboard:female:1003",
      "wr_id": 1003,
      "name": "우질",
      "reason": "user_excluded_unneeded_for_homepage",
      "updated_at": "2026-05-15T15:03:41.507Z"
    },
    {
      "entity_id": "eloboard:female:955",
      "wr_id": 955,
      "name": "찡찡시아",
      "reason": "user_excluded_unneeded_for_homepage",
      "updated_at": "2026-05-15T15:03:41.507Z"
    },
    {
      "entity_id": "eloboard:male:mix:1068",
      "wr_id": 1068,
      "name": "두폴조합",
      "reason": "user_excluded",
      "updated_at": "2026-04-09T00:00:00.000Z"
    },
    {
      "entity_id": "eloboard:male:mix:192",
      "wr_id": 192,
      "name": "강만식",
      "reason": "user_excluded_unneeded_for_homepage",
      "updated_at": "2026-05-15T15:03:41.507Z"
    },
    {
      "entity_id": "eloboard:female:352",
      "wr_id": 352,
      "name": "김하선",
      "reason": "user_excluded_unneeded_for_homepage",
      "updated_at": "2026-05-15T15:03:41.507Z"
    },
    {
      "entity_id": "eloboard:male:mix:395",
      "wr_id": 395,
      "name": "서도일",
      "reason": "user_excluded_unneeded_for_homepage",
      "updated_at": "2026-05-15T15:04:33.106Z"
    },
    {
      "name": "저라뎃",
      "reason": "user_excluded",
      "updated_at": "2026-04-10T00:00:00.000Z"
    },
    {
      "name": "밍도릿",
      "reason": "user_excluded",
      "updated_at": "2026-04-10T00:00:00.000Z"
    },
    {
      "name": "뀨알",
      "reason": "user_excluded",
      "updated_at": "2026-04-10T00:00:00.000Z"
    },
    {
      "name": "뀨알",
      "reason": "user_excluded",
      "updated_at": "2026-04-17T00:00:00.000Z"
    },
    {
      "entity_id": "eloboard:male:66",
      "wr_id": 66,
      "name": "박지수",
      "reason": "user_excluded_unneeded_for_homepage",
      "updated_at": "2026-05-15T15:04:33.106Z"
    },
    {
      "entity_id": "eloboard:male:118",
      "wr_id": 118,
      "name": "김수환",
      "reason": "user_excluded_unneeded_for_homepage",
      "updated_at": "2026-05-15T15:03:41.507Z"
    },
    {
      "entity_id": "eloboard:male:mix:256",
      "wr_id": 256,
      "name": "수입뿌드",
      "reason": "user_excluded_unneeded_for_homepage",
      "updated_at": "2026-05-15T15:04:33.106Z"
    },
    {
      "entity_id": "eloboard:male:mix:329",
      "wr_id": 329,
      "name": "카리스",
      "reason": "user_excluded_unneeded_for_homepage",
      "updated_at": "2026-05-15T15:04:33.106Z"
    },
    {
      "entity_id": "eloboard:male:mix:347",
      "wr_id": 347,
      "name": "트할",
      "reason": "user_excluded_unneeded_for_homepage",
      "updated_at": "2026-05-15T15:04:33.106Z"
    },
    {
      "entity_id": "eloboard:female:856",
      "wr_id": 856,
      "name": "한소끔",
      "reason": "user_excluded_unneeded_for_homepage",
      "updated_at": "2026-05-15T17:50:27.873Z"
    },
    {
      "entity_id": "eloboard:female:999",
      "wr_id": 999,
      "name": "연또",
      "reason": "retired_profile_after_race_change",
      "updated_at": "2026-04-20T00:00:00.000Z"
    },
    {
      "entity_id": "eloboard:female:889",
      "wr_id": 889,
      "name": "Hiyoko",
      "reason": "user_excluded_retired_or_unneeded",
      "updated_at": "2026-04-26T00:00:00.000+09:00"
    },
    {
      "entity_id": "eloboard:male:123",
      "wr_id": 123,
      "name": "오은유",
      "reason": "user_excluded_unneeded_for_homepage",
      "updated_at": "2026-05-15T15:04:33.106Z"
    },
    {
      "entity_id": "eloboard:male:mix:159",
      "wr_id": 159,
      "name": "저라뎃",
      "reason": "user_excluded_unneeded_for_homepage",
      "updated_at": "2026-05-15T13:51:21.994Z"
    },
    {
      "entity_id": "eloboard:male:199",
      "wr_id": 199,
      "name": "탱크",
      "reason": "user_excluded_unneeded_for_homepage",
      "updated_at": "2026-05-15T15:01:05.440Z"
    },
    {
      "entity_id": "eloboard:female:776",
      "wr_id": 776,
      "name": "밍도릿",
      "reason": "user_excluded_unneeded_for_homepage",
      "updated_at": "2026-05-15T15:01:05.440Z"
    },
    {
      "entity_id": "eloboard:female:965",
      "wr_id": 965,
      "name": "뀨알",
      "reason": "user_excluded_unneeded_for_homepage",
      "updated_at": "2026-05-15T15:01:05.440Z"
    },
    {
      "entity_id": "eloboard:female:354",
      "wr_id": 354,
      "name": "햄찌야",
      "reason": "user_excluded_unneeded_for_homepage",
      "updated_at": "2026-05-15T15:03:41.507Z"
    },
    {
      "entity_id": "eloboard:male:185",
      "wr_id": 185,
      "name": "박한별",
      "reason": "user_excluded_unneeded_for_homepage",
      "updated_at": "2026-05-15T15:04:33.106Z"
    },
    {
      "entity_id": "eloboard:male:mix:777",
      "wr_id": 777,
      "name": "엘사",
      "reason": "user_excluded_unneeded_for_homepage",
      "updated_at": "2026-05-15T15:04:33.106Z"
    },
    {
      "entity_id": "eloboard:male:mix:831",
      "wr_id": 831,
      "name": "니칸",
      "reason": "user_excluded_unneeded_for_homepage",
      "updated_at": "2026-05-15T17:50:27.873Z"
    },
    {
      "entity_id": "eloboard:male:mix:377",
      "wr_id": 377,
      "name": "모토케이",
      "reason": "user_excluded_unneeded_for_homepage",
      "updated_at": "2026-05-15T17:50:27.873Z"
    },
    {
      "entity_id": "eloboard:female:1033",
      "wr_id": 1033,
      "name": "성예린",
      "reason": "user_excluded_unneeded_for_homepage",
      "updated_at": "2026-05-15T17:50:27.873Z"
    },
    {
      "entity_id": "eloboard:female:1007",
      "name": "땃쥐",
      "wr_id": 1007,
      "reason": "superseded_identity_race_change",
      "note": "Eloboard issues a new wr_id on race change. 1007(Protoss) was superseded by 1015(Zerg); 1015 is the current identity (user-confirmed 2026-07-20)."
    },
    {
      "entity_id": "eloboard:female:1046",
      "name": "슬아",
      "wr_id": 1046,
      "reason": "superseded_identity_race_change",
      "note": "Merged into eloboard:female:57, which is the current identity (user-confirmed 2026-07-20)."
    },
    {
      "entity_id": "eloboard:female:1031",
      "wr_id": 1031,
      "name": "이영숙",
      "reason": "user_excluded_unneeded_for_homepage",
      "note": "운영자 확인 2026-07-23: 예전 자료의 외부인. 기록·사이트 표시 모두 불필요.",
      "updated_at": "2026-07-23T05:44:50.872Z"
    },
    {
      "entity_id": "eloboard:male:mix:810",
      "wr_id": 810,
      "name": "지방시",
      "reason": "user_excluded_unneeded_for_homepage",
      "note": "운영자 확인 2026-07-23: 기록 정리·사이트 표시 모두 불필요.",
      "updated_at": "2026-07-23T05:44:50.872Z"
    }
  ]
}
